[{"currency":"dolar ameryka\u0144ski","code":"USD","ask":4.2426,"bid":4.3284},{"currency":"dolar australijski","code":"AUD","ask":3.0059,"bid":3.0667},{"currency":"dolar kanadyjski","code":"CAD","ask":3.3144,"bid":3.3814},{"currency":"euro","code":"EUR","ask":4.5545,"bid":4.6465},{"currency":"forint (W\u0119gry)","code":"HUF","ask":0.01189,"bid":0.01213},{"currency":"frank szwajcarski","code":"CHF","ask":4.4182,"bid":4.5074},{"currency":"funt szterling","code":"GBP","ask":5.3086,"bid":5.4158},{"currency":"jen (Japonia)","code":"JPY","ask":0.033488,"bid":0.034164},{"currency":"korona czeska","code":"CZK","ask":0.1847,"bid":0.1885},{"currency":"korona du\u0144ska","code":"DKK","ask":0.6121,"bid":0.6245},{"currency":"korona norweska","code":"NOK","ask":0.4426,"bid":0.4516},{"currency":"korona szwedzka","code":"SEK","ask":0.4334,"bid":0.4422},{"currency":"SDR (MFW)","code":"XDR","ask":5.7670,"bid":5.8836},{"currency":"polski z\u0142oty","code":"PLN","ask":1,"bid":1}]